adam_assist-0.3.4.dist-info/METADATA
adam_assist-0.3.4.dist-info/WHEEL
adam_assist-0.3.4.dist-info/entry_points.txt
adam_assist-0.3.4.dist-info/licenses/LICENSE
adam_assist/__init__.py
adam_assist/propagator.py
adam_assist/version.py
adam_assist-0.3.4.dist-info/RECORD
