Metadata-Version: 2.1
Name: adam-assist
Version: 0.3.4
Summary: ADAM Core Propagator class using ASSIST
Keywords: astronomy,orbital mechanics,propagation
Author: Kathleen Kiker
Author-Email: Alec Koumjian <akoumjian@gmail.com>
License: GNU GENERAL PUBLIC LICENSE
Classifier: Development Status :: 4 - Beta
Classifier: Intended Audience :: Science/Research
Classifier: License :: OSI Approved :: GNU General Public License v3 (GPLv3)
Classifier: Programming Language :: Python
Classifier: Programming Language :: Python :: 3
Classifier: Topic :: Scientific/Engineering :: Astronomy
Project-URL: Documentation, https://github.com/B612-Asteroid-Institute/adam-assist#readme
Project-URL: Issues, https://github.com/B612-Asteroid-Institute/adam-assist/issues
Project-URL: Source, https://github.com/B612-Asteroid-Institute/adam-assist
Requires-Python: <3.13,>3.11.0
Requires-Dist: adam-core>=0.4.0
Requires-Dist: naif-de440
Requires-Dist: jpl-small-bodies-de441-n16
Requires-Dist: assist-adam-fork==1.1.9.post1
Requires-Dist: numpy
Requires-Dist: ray
Requires-Dist: spiceypy>=6.0.0
Requires-Dist: rebound>=4.4.10
Requires-Dist: timezonefinder==8.0.0
Provides-Extra: dev
Requires-Dist: ruff; extra == "dev"
Requires-Dist: pdm; extra == "dev"
Requires-Dist: mypy; extra == "dev"
Requires-Dist: pytest; extra == "dev"
Requires-Dist: pytest-cov; extra == "dev"
Requires-Dist: pytest-mock; extra == "dev"
Requires-Dist: pytest-benchmark; extra == "dev"
Requires-Dist: scalene>=1.5.53; extra == "dev"
Requires-Dist: py-spy>=0.4.1; extra == "dev"
Requires-Dist: snakeviz>=2.2.2; extra == "dev"
Requires-Dist: line-profiler>=5.0.0; extra == "dev"
Requires-Dist: black; extra == "dev"
Requires-Dist: isort; extra == "dev"
Requires-Dist: ipython; extra == "dev"
